fakturoid/__init__.py
fakturoid/api.py
fakturoid/models.py
fakturoid/paging.py
fakturoid/six.py
fakturoid_v3-2025.0.0.dist-info/METADATA
fakturoid_v3-2025.0.0.dist-info/WHEEL
fakturoid_v3-2025.0.0.dist-info/RECORD
