Metadata-Version: 2.4
Name: fakturoid-v3
Version: 2025.0.0
Summary: The Python interface to online accounting service [Fakturoid](http://fakturoid.cz/).
Project-URL: Homepage, https://github.com/jarovo/python-fakturoid-v3/
Project-URL: Repository, https://github.com/jarovo/python-fakturoid-v3/
Author-email: Roman Krejcik <farin@farin.cz>, Jaroslav Henner <jaroslav.henner@gmail.com>
Maintainer-email: Jaroslav Henner <jaroslav.henner@gmail.com>
License-Expression: MIT
Keywords: accounting,fakturoid
Classifier: Development Status :: 5 - Production/Stable
Classifier: Intended Audience :: Developers
Classifier: License :: OSI Approved :: MIT License
Classifier: Operating System :: OS Independent
Classifier: Programming Language :: Python :: 2.6
Classifier: Programming Language :: Python :: 2.7
Classifier: Programming Language :: Python :: 3
Classifier: Topic :: Office/Business :: Financial :: Accounting
Requires-Python: >=3.8
Requires-Dist: python-dateutil
Requires-Dist: requests
